README.md
setup.py
yt_video_scraper_python/__init__.py
yt_video_scraper_python.egg-info/PKG-INFO
yt_video_scraper_python.egg-info/SOURCES.txt
yt_video_scraper_python.egg-info/dependency_links.txt
yt_video_scraper_python.egg-info/requires.txt
yt_video_scraper_python.egg-info/top_level.txt