Metadata-Version: 2.1
Name: yt-video-scraper-python
Version: 1.0.0
Summary: A python library to scrape video data from youtube automatically.
Home-page: https://youtube-api.datakund.com/en/latest/
Author: DataKund
Author-email: datakund@gmail.com
License: Apache License 2.0
Keywords: youtube python btstudio video info scraper data web-scraping
Platform: UNKNOWN
